fasttrain/__init__.py
fasttrain/metrics.py
fasttrain/reproduce.py
fasttrain/callbacks/__init__.py
fasttrain/callbacks/callback.py
fasttrain/callbacks/checkpoint.py
fasttrain/callbacks/early_stopping.py
fasttrain/callbacks/progress_bar.py
fasttrain/train/__init__.py
fasttrain/train/device.py
fasttrain/train/history.py
fasttrain/train/trainer.py
fasttrain-0.0.7.dist-info/LICENSE
fasttrain-0.0.7.dist-info/METADATA
fasttrain-0.0.7.dist-info/WHEEL
fasttrain-0.0.7.dist-info/top_level.txt
fasttrain-0.0.7.dist-info/RECORD
