Metadata-Version: 2.1
Name: fasttrain
Version: 0.0.7
Summary: Framework for building training loops easier and faster
Home-page: https://github.com/samedit66/fasttrain
Author: samedit66
Author-email: samedit66@yandex.ru
License: Apache 2.0 License
Keywords: python torch pytorch
Classifier: Programming Language :: Python :: 3
Classifier: Operating System :: OS Independent
Requires-Python: >=3.7
License-File: LICENSE
Requires-Dist: torch
Requires-Dist: tqdm
Requires-Dist: numpy
Requires-Dist: matplotlib
Requires-Dist: scipy
